{
  "id": "google-drive",
  "name": "Google Drive",
  "category": "document-integration",
  "requires_api_key": true,
  "logo": "/assets/google-drive.png",
  "openwebui_variables": [
    {
      "name": "ENABLE_GOOGLE_DRIVE_INTEGRATION",
      "type": "bool",
      "default": "False",
      "description": "Enables or disables Google Drive integration. If set to true, and `GOOGLE_DRIVE_CLIENT_ID` & `GOOGLE_DRIVE_API_KEY` are both configured, Google Drive will appear as an upload option in the chat UI.",
      "options": []
    },
    {
      "name": "GOOGLE_DRIVE_API_KEY",
      "type": "str",
      "default": null,
      "description": "Sets the API key for Google Drive integration.",
      "options": []
    },
    {
      "name": "GOOGLE_DRIVE_CLIENT_ID",
      "type": "str",
      "default": null,
      "description": "Sets the client ID for Google Drive (client must be configured with Drive API and Picker API enabled).",
      "options": []
    }
  ]
}